bkw_python/__init__.py
bkw_python/data_models.py
bkw_python/exceptions.py
bkw_python/operation_helpers.py
bkw_python/operation_models.py
bkw_python/rest_adapter.py
bkw_python-0.0.4.dist-info/METADATA
bkw_python-0.0.4.dist-info/WHEEL
bkw_python-0.0.4.dist-info/licenses/LICENSE
bkw_python-0.0.4.dist-info/RECORD
