Metadata-Version: 2.1
Name: bkw-python
Version: 0.0.4
Summary: A limited Python client for the BankruptcyWatch API.
Project-URL: Homepage, https://github.com/ryangustaf/bkw-python
Project-URL: Bug Tracker, https://github.com/ryangustaf/bkw-python/issues
Author-email: Ryan Stone <ryan@bankruptcywatch.com>
License-File: LICENSE
Classifier: License :: OSI Approved :: MIT License
Classifier: Operating System :: OS Independent
Classifier: Programming Language :: Python :: 3
Requires-Python: >=3.7
Requires-Dist: future
Requires-Dist: pydantic
Requires-Dist: pytest
Requires-Dist: requests
Requires-Dist: requests-mock
Requires-Dist: xmltodict
